sprintsolo_sally_db_client/__init__.py
sprintsolo_sally_db_client/__main__.py
sprintsolo_sally_db_client/_async_http.py
sprintsolo_sally_db_client/_base_client.py
sprintsolo_sally_db_client/_builder.py
sprintsolo_sally_db_client/_compat.py
sprintsolo_sally_db_client/_config.py
sprintsolo_sally_db_client/_constants.py
sprintsolo_sally_db_client/_fields.py
sprintsolo_sally_db_client/_metrics.py
sprintsolo_sally_db_client/_proxy.py
sprintsolo_sally_db_client/_raw_query.py
sprintsolo_sally_db_client/_registry.py
sprintsolo_sally_db_client/_sync_http.py
sprintsolo_sally_db_client/_transactions.py
sprintsolo_sally_db_client/_types.py
sprintsolo_sally_db_client/_typing.py
sprintsolo_sally_db_client/actions.py
sprintsolo_sally_db_client/bases.py
sprintsolo_sally_db_client/client.py
sprintsolo_sally_db_client/enums.py
sprintsolo_sally_db_client/errors.py
sprintsolo_sally_db_client/fields.py
sprintsolo_sally_db_client/http.py
sprintsolo_sally_db_client/http_abstract.py
sprintsolo_sally_db_client/metadata.py
sprintsolo_sally_db_client/models.py
sprintsolo_sally_db_client/mypy.py
sprintsolo_sally_db_client/partials.py
sprintsolo_sally_db_client/py.typed
sprintsolo_sally_db_client/schema.prisma
sprintsolo_sally_db_client/testing.py
sprintsolo_sally_db_client/types.py
sprintsolo_sally_db_client/utils.py
sprintsolo_sally_db_client/validator.py
sprintsolo_sally_db_client/_vendor/__init__.py
sprintsolo_sally_db_client/_vendor/lark_schema_parser.py
sprintsolo_sally_db_client/_vendor/lark_schema_scan_parser.py
sprintsolo_sally_db_client/binaries/__init__.py
sprintsolo_sally_db_client/binaries/constants.py
sprintsolo_sally_db_client/binaries/platform.py
sprintsolo_sally_db_client/cli/__init__.py
sprintsolo_sally_db_client/cli/_node.py
sprintsolo_sally_db_client/cli/cli.py
sprintsolo_sally_db_client/cli/custom.py
sprintsolo_sally_db_client/cli/options.py
sprintsolo_sally_db_client/cli/prisma.py
sprintsolo_sally_db_client/cli/utils.py
sprintsolo_sally_db_client/cli/commands/__init__.py
sprintsolo_sally_db_client-0.1.50.dist-info/METADATA
sprintsolo_sally_db_client-0.1.50.dist-info/WHEEL
sprintsolo_sally_db_client-0.1.50.dist-info/top_level.txt
sprintsolo_sally_db_client-0.1.50.dist-info/RECORD
