Metadata-Version: 2.4
Name: sprintsolo-sally-db-client
Version: 0.1.50
Summary: Prisma Python client for organization services (generated in central repo)
License: UNLICENSED
Requires-Python: >=3.11
